{
  "editor.formatOnSave": true,
  "editor.formatOnPaste": true,
  "emmet.triggerExpansionOnTab": true,
  "emmet.includeLanguages": {
    "javascript": "javascriptreact",
    "typescript": "typescriptreact"
  },
  "[javascript]": {
    "editor.codeActionsOnSave": {
      "source.fixAll.eslint": true
    }
  },
  "[typescript]": {
    "editor.codeActionsOnSave": {
      "source.fixAll.eslint": true
    }
  },
  "[typescriptreact]": {
    "editor.codeActionsOnSave": {
      "source.fixAll.eslint": true
    }
  },
  "[scss]": {
    "editor.codeActionsOnSave": {
      "source.fixAll.stylelint": true
    }
  }
}
